yanghao/__init__.py
yanghao/portlink/__init__.py
yanghao/portlink/client.py
yanghao_portlink-0.0.15.dist-info/METADATA
yanghao_portlink-0.0.15.dist-info/WHEEL
yanghao_portlink-0.0.15.dist-info/entry_points.txt
yanghao_portlink-0.0.15.dist-info/top_level.txt
yanghao_portlink-0.0.15.dist-info/RECORD
