Metadata-Version: 2.4
Name: yanghao.portlink
Version: 0.0.15
Summary: Simple TCP public network tunnel
Author-email: Yang Hao <fexeak@163.com>
Project-URL: Homepage, https://github.com/yahao333/portlink
Project-URL: Bug Tracker, https://github.com/yahao333/portlink/issues
Classifier: Programming Language :: Python :: 3
Classifier: License :: OSI Approved :: MIT License
Classifier: Operating System :: OS Independent
Requires-Python: >=3.7
Requires-Dist: websockets
